madmac.py
madmac-1.0.1.dist-info/LICENSE
madmac-1.0.1.dist-info/METADATA
madmac-1.0.1.dist-info/WHEEL
madmac-1.0.1.dist-info/entry_points.txt
madmac-1.0.1.dist-info/top_level.txt
madmac-1.0.1.dist-info/RECORD
