Metadata-Version: 2.1
Name: madmac
Version: 1.0.1
Summary: madmac: MAC address generator
Home-page: https://github.com/laminko/madmac
Author: lmk
Author-email: lminko.lmk@gmail.com
License: MIT
Platform: UNKNOWN
Classifier: License :: OSI Approved :: MIT License
Classifier: Programming Language :: Python
Classifier: Programming Language :: Python :: 3
Classifier: Programming Language :: Python :: 3.5
Classifier: Programming Language :: Python :: Implementation :: CPython
Classifier: Programming Language :: Python :: Implementation :: PyPy
Requires-Python: >=3.5.2
